odoo/addons/sale_report_delivered_volume/README.rst
odoo/addons/sale_report_delivered_volume/__init__.py
odoo/addons/sale_report_delivered_volume/__manifest__.py
odoo/addons/sale_report_delivered_volume/i18n/es.po
odoo/addons/sale_report_delivered_volume/i18n/it.po
odoo/addons/sale_report_delivered_volume/i18n/sale_report_delivered_volume.pot
odoo/addons/sale_report_delivered_volume/models/__init__.py
odoo/addons/sale_report_delivered_volume/models/sale_report.py
odoo/addons/sale_report_delivered_volume/readme/CONTRIBUTORS.md
odoo/addons/sale_report_delivered_volume/readme/DESCRIPTION.md
odoo/addons/sale_report_delivered_volume/readme/USAGE.md
odoo/addons/sale_report_delivered_volume/static/description/icon.png
odoo/addons/sale_report_delivered_volume/static/description/index.html
odoo/addons/sale_report_delivered_volume/tests/__init__.py
odoo/addons/sale_report_delivered_volume/tests/test_sale_report_delivered_volume.py
odoo_addon_sale_report_delivered_volume-18.0.1.0.0.2.dist-info/METADATA
odoo_addon_sale_report_delivered_volume-18.0.1.0.0.2.dist-info/WHEEL
odoo_addon_sale_report_delivered_volume-18.0.1.0.0.2.dist-info/top_level.txt
odoo_addon_sale_report_delivered_volume-18.0.1.0.0.2.dist-info/RECORD
